encoder8x3/encoder8x3.srcs/sources_1/new/encoder8x3.v
module encoder_8x3(out, in);
output [2:0] out; input [7:0] in;
assign out[0] = in[1] + in[3] + in[5] + in[7];
assign out[1] = in[2] + in[3] + in[6] + in[7];
assign out[2] = in[4] + in[5] + in[6] + in[7];
endmodule

encoder8x3/encoder8x3.srcs/sim_1/new/encoder_8x3_tb.v
module testbench;
reg [7:0]in;
wire [2:0]out;
encoder_8x3 enc(out, in);
initial
begin
in = 8'b00000001;
#10 in = 8'b00000010;
#10in = 8'b00000100;
#10 in = 8'b00001000;
#10 in = 8'b00010000;
#10 in = 8'b00100000;
#10 in = 8'b01000000;
#10 in = 8'b10000000;
#10 $finish;
end
initial
begin
$display("i/p and o/p are");
$monitor("in= %b and y= %b",in,out);
$dumpfile("test.vcd");
$dumpvars(0,testbench);
end endmodule

encoder8x3/encoder8x3.sim/sim_1/behav/xsim/test.vcd
$date
   Mon Dec  5 12:51:42 2022
$end
$version
  2020.1
$end
$timescale
  1ps
$end
$scope module testbench $end
$var reg 8 ! in [7:0] $end
$var wire 3 " out [2:0] $end
$scope module enc $end
$var wire 3 " out [2:0] $end
$var wire 8 # in [7:0] $end
$upscope $end
$upscope $end
$enddefinitions $end
#0
$dumpvars
b1 !
b0 "
b1 #
$end
#10000
b10 !
b1 "
b10 #
#20000
b100 !
b10 "
b100 #
#30000
b1000 !
b11 "
b1000 #
#40000
b10000 !
b100 "
b10000 #
#50000
b100000 !
b101 "
b100000 #
#60000
b1000000 !
b110 "
b1000000 #
#70000
b10000000 !
b111 "
b10000000 #
