full adder/full adder.srcs/sources_1/new/full_adder.v
module fulladder(s,cout,a,b,cin);
  input a,b,cin;
  output s,cout;
  assign s = a^b^cin;
  assign cout = a&b | cin & (a^b);
endmodule

full adder/full adder.srcs/sim_1/new/full_adder_tb.v

module fulladder_tb;
  reg a,b,cin;
  wire s,cout;
 
  fulladder lut(s,cout,a,b,cin);
 
  initial
    begin
      a=00;b=00; cin = 0;
      #100; a = 0;b = 0;cin = 1;
      #100; a = 0;b = 1;cin = 0;
      #100; a = 0;b = 1;cin = 1;
      #100; a = 1;b = 0;cin = 0;
      #100; a = 1;b = 0;cin = 1;
      #100; a = 1;b = 1;cin = 0;
      #100; a = 1;b = 1;cin = 1;
      #100 $finish;
     
    end
 
  initial
  begin
    $display("i/p and o/p are");
    $monitor("a= %b,b= %b,cin=%b, s= %b,cout= %b",a,b,cin,s,cout);
    $dumpfile("test.vcd");
    $dumpvars(0,fulladder_tb);
    //$dumpvars;
  end
 
endmodule

full adder/full adder.sim/sim_1/behav/xsim/test.vcd
$date
   Mon Dec  5 11:21:56 2022
$end
$version
  2020.1
$end
$timescale
  1ps
$end
$scope module fulladder_tb $end
$var reg 1 ! a $end
$var reg 1 " b $end
$var reg 1 # cin $end
$var wire 1 $ s $end
$var wire 1 % cout $end
$scope module lut $end
$var wire 1 & a $end
$var wire 1 ' b $end
$var wire 1 ( cin $end
$var wire 1 $ s $end
$var wire 1 % cout $end
$upscope $end
$upscope $end
$enddefinitions $end
#0
$dumpvars
0!
0"
0#
0$
0%
0&
0'
0(
$end
#100000
1#
1$
0%
1(
#200000
1"
0#
1$
0%
1'
0(
#300000
1#
0$
1%
1(
#400000
1!
0"
0#
1$
0%
1&
0'
0(
#500000
1#
0$
1%
1(
#600000
1"
0#
0$
1%
1'
0(
#700000
1#
1$
1%
1(
